Metadata-Version: 2.4
Name: apache-airflow-providers-fastetl
Version: 0.2.10
Summary: FastETL custom package Apache Airflow provider.
Home-page: https://github.com/gestaogovbr/FastETL
Author: Time de Dados CGINF
Author-email: seges.cginf@economia.gov.br
License: Apache License 2.0
Classifier: Framework :: Apache Airflow
Classifier: Framework :: Apache Airflow :: Provider
Requires-Python: ~=3.8
License-File: LICENSE
Requires-Dist: apache-airflow>=2.3
Requires-Dist: apache-airflow-providers-microsoft-mssql
Requires-Dist: apache-airflow-providers-mysql
Requires-Dist: apache-airflow-providers-postgres
Requires-Dist: apache-airflow-providers-common-sql
Requires-Dist: alembic>=1.8.1
Requires-Dist: beautifulsoup4>=4.1.11
Requires-Dist: ckanapi>=4.6
Requires-Dist: frictionless>=5.11.1
Requires-Dist: markdown>=3.4.1
Requires-Dist: odfpy>=1.4.1
Requires-Dist: pandas<2,>=1.5.2
Requires-Dist: psycopg2>=2.9.5
Requires-Dist: pygsheets>=2.0.5
Requires-Dist: pyodbc>=4.0.35
Requires-Dist: pysmb>=1.2.6
Requires-Dist: python-slugify>=7.0.0
Requires-Dist: pytz>=2022.6
Requires-Dist: requests>=2.28.1
Requires-Dist: SQLAlchemy>=1.4.44
Requires-Dist: PyYAML==6.0
Requires-Dist: openmetadata-ingestion==1.5.2.0
Dynamic: author
Dynamic: author-email
Dynamic: classifier
Dynamic: description
Dynamic: description-content-type
Dynamic: home-page
Dynamic: license
Dynamic: license-file
Dynamic: requires-dist
Dynamic: requires-python
Dynamic: summary
